MANIFEST.in
README.md
requirements.txt
setup.py
tornadis/__init__.py
tornadis/benchmark.py
tornadis/client.py
tornadis/connection.py
tornadis/exceptions.py
tornadis/pipeline.py
tornadis/pool.py
tornadis/pubsub.py
tornadis/state.py
tornadis/utils.py
tornadis/write_buffer.py
tornadis.egg-info/PKG-INFO
tornadis.egg-info/SOURCES.txt
tornadis.egg-info/dependency_links.txt
tornadis.egg-info/entry_points.txt
tornadis.egg-info/requires.txt
tornadis.egg-info/top_level.txt