Metadata-Version: 1.1
Name: tornadis
Version: 0.8.1
Summary: tornadis is an async minimal redis client for tornado ioloop designed for performances (use C hiredis parser)
Home-page: https://github.com/thefab/tornadis
Author: Fabien MARTY
Author-email: fabien.marty@gmail.com
License: MIT
Download-URL: https://github.com/thefab/tornadis
Platform: UNKNOWN
Classifier: Development Status :: 4 - Beta
Classifier: Environment :: Console
Classifier: Intended Audience :: Developers
Classifier: Intended Audience :: System Administrators
Classifier: License :: OSI Approved :: MIT License
Classifier: Operating System :: MacOS :: MacOS X
Classifier: Operating System :: POSIX
Classifier: Operating System :: Unix
Classifier: Programming Language :: Python :: 2.7
Classifier: Programming Language :: Python :: 3.2
Classifier: Programming Language :: Python :: 3.3
Classifier: Programming Language :: Python :: 3.4
Classifier: Programming Language :: Python :: 3.5
Classifier: Programming Language :: Python :: 3.6
Classifier: Topic :: Utilities
Classifier: Topic :: System :: Distributed Computing
Classifier: Topic :: Software Development
